timeit_magic.py
timeit_magic-0.2.2.dist-info/LICENSE
timeit_magic-0.2.2.dist-info/METADATA
timeit_magic-0.2.2.dist-info/WHEEL
timeit_magic-0.2.2.dist-info/top_level.txt
timeit_magic-0.2.2.dist-info/RECORD
